stride/__init__.py
stride/__main__.py
stride/cli.py
stride/config.py
stride/constants.py
stride/models.py
stride/utils.py
stride/commands/__init__.py
stride/commands/init.py
stride/commands/list.py
stride/commands/metrics.py
stride/commands/show.py
stride/commands/status.py
stride/commands/validate.py
stride/core/__init__.py
stride/core/agent_registry.py
stride/core/analytics.py
stride/core/analytics_cache.py
stride/core/file_manager.py
stride/core/markdown_parser.py
stride/core/metrics_calculator.py
stride/core/sprint_manager.py
stride/core/sprint_parser.py
stride/core/template_converter.py
stride/core/validator.py
stride/templates/__init__.py
stride/templates/agent_commands/complete.md
stride/templates/agent_commands/derive.md
stride/templates/agent_commands/feedback.md
stride/templates/agent_commands/implement.md
stride/templates/agent_commands/init.md
stride/templates/agent_commands/lite.md
stride/templates/agent_commands/plan.md
stride/templates/agent_commands/present.md
stride/templates/agent_commands/review.md
stride/templates/agent_commands/status.md
stride/templates/agents_docs/internal.md
stride/templates/agents_docs/root.md
stride/templates/sprint_files/design.md
stride/templates/sprint_files/implementation.md
stride/templates/sprint_files/plan.md
stride/templates/sprint_files/project.md
stride/templates/sprint_files/proposal.md
stride/templates/sprint_files/retrospective.md
stridekit-1.0.1.dist-info/licenses/LICENSE
stridekit-1.0.1.dist-info/METADATA
stridekit-1.0.1.dist-info/WHEEL
stridekit-1.0.1.dist-info/entry_points.txt
stridekit-1.0.1.dist-info/top_level.txt
stridekit-1.0.1.dist-info/RECORD
