Metadata-Version: 2.4
Name: stridekit
Version: 1.0.1
Summary: An Agent-First Framework for Sprint-Powered, Spec-Driven Development
Author: Saran Mahadev
License: MIT
Project-URL: Homepage, https://stride.saranmahadev.in
Project-URL: Documentation, https://stride.saranmahadev.in
Project-URL: Repository, https://github.com/saranmahadev/Stride.git
Project-URL: Issues, https://github.com/saranmahadev/Stride/issues
Project-URL: Source, https://github.com/saranmahadev/Stride
Keywords: cli,sprint,agile,ai-agent,development,stride,workflow
Classifier: Development Status :: 5 - Production/Stable
Classifier: Intended Audience :: Developers
Classifier: Topic :: Software Development :: Build Tools
Classifier: License :: OSI Approved :: MIT License
Classifier: Programming Language :: Python :: 3
Classifier: Programming Language :: Python :: 3.8
Classifier: Programming Language :: Python :: 3.9
Classifier: Programming Language :: Python :: 3.10
Classifier: Programming Language :: Python :: 3.11
Classifier: Programming Language :: Python :: 3.12
Requires-Python: >=3.8
License-File: LICENSE
Requires-Dist: typer[all]>=0.9.0
Requires-Dist: rich>=13.0.0
Requires-Dist: pyyaml>=6.0.0
Requires-Dist: pydantic>=2.0.0
Requires-Dist: pyfiglet>=0.8.post1
Requires-Dist: questionary>=2.0.0
Provides-Extra: dev
Requires-Dist: pytest>=7.0.0; extra == "dev"
Requires-Dist: pytest-cov>=4.0.0; extra == "dev"
Requires-Dist: black>=23.0.0; extra == "dev"
Requires-Dist: isort>=5.12.0; extra == "dev"
Requires-Dist: mypy>=1.0.0; extra == "dev"
Provides-Extra: docs
Requires-Dist: mkdocs>=1.5.0; extra == "docs"
Requires-Dist: mkdocs-material>=9.5.0; extra == "docs"
Requires-Dist: mkdocs-git-revision-date-localized-plugin>=1.2.0; extra == "docs"
Dynamic: license-file
